aio_message_handler/__init__.py
aio_message_handler/consumer.py
aio_message_handler/exceptions.py
aio_message_handler/handler.py
aio_message_handler/version.py
aio_message_handler-0.0.4.dist-info/LICENSE
aio_message_handler-0.0.4.dist-info/METADATA
aio_message_handler-0.0.4.dist-info/WHEEL
aio_message_handler-0.0.4.dist-info/top_level.txt
aio_message_handler-0.0.4.dist-info/RECORD
